{
  "as_of": "2026-07-16T16:15:57Z",
  "update_time": "01:15 KST",
  "nasdaq": {
    "price": 26006.73,
    "change_pct": -1.0,
    "dist_to_masam_pct": 3.0,
    "from_ath_pct": -4.0,
    "last_masam_date": "2026-06-05"
  },
  "sp500": {
    "price": 7546.68,
    "change_pct": -0.34
  },
  "dow": {
    "price": 52671.27,
    "change_pct": 0.02
  },
  "rank1": {
    "ticker": "NVDA",
    "name": "엔비디아",
    "domain": "nvidia.com",
    "si": "nvidia/76b900",
    "price": 206.66,
    "change_pct": -2.75,
    "ath": 235.74,
    "intra_low": 191.14
  },
  "rank2": {
    "ticker": "AAPL",
    "price": 330.79,
    "change_pct": 1.0,
    "ath": 330.79,
    "intra_low": 307.0
  },
  "qqq": {
    "price": 707.87,
    "change_pct": -1.38,
    "ath": 746.16,
    "intra_low": 700.91
  },
  "hedges": {
    "TLT": 84.01,
    "IAU": 75.02,
    "GLD": 366.06,
    "TIP": 107.97
  },
  "mcap_live": {
    "NVDA": {
      "change_pct": -2.17
    },
    "AAPL": {
      "change_pct": 0.92
    },
    "GOOGL": {
      "change_pct": -0.22
    },
    "MSFT": {
      "change_pct": 0.72
    },
    "AMZN": {
      "change_pct": 0.31
    },
    "TSM": {
      "change_pct": -4.03
    },
    "AVGO": {
      "change_pct": -3.34
    },
    "SPCX": {
      "change_pct": -1.9
    },
    "META": {
      "change_pct": -1.42
    },
    "2222.SR": {
      "change_pct": 0.3
    },
    "TSLA": {
      "change_pct": -1.54
    },
    "005930.KS": {
      "change_pct": -8.77
    },
    "BRK-B": {
      "change_pct": -0.16
    },
    "LLY": {
      "change_pct": 1.68
    },
    "MU": {
      "change_pct": -5.36
    },
    "JPM": {
      "change_pct": -0.58
    },
    "000660.KS": {
      "change_pct": -11.53
    },
    "WMT": {
      "change_pct": 1.58
    },
    "AMD": {
      "change_pct": -5.29
    },
    "ASML": {
      "change_pct": -0.14
    },
    "V": {
      "change_pct": 1.7
    },
    "XOM": {
      "change_pct": 1.5
    },
    "JNJ": {
      "change_pct": 0.67
    },
    "TCEHY": {
      "change_pct": -0.24
    },
    "INTC": {
      "change_pct": -5.62
    }
  },
  "live_market": {
    "vix": 16.03,
    "vix_chg": 2.3,
    "usd_krw": 1479.2,
    "usd_krw_chg": -0.58,
    "fear_greed": 47
  }
}