{
  "as_of": "2026-06-23",
  "rank1_ticker": "NVDA",
  "items": [
    {
      "rank": 1,
      "ticker": "NVDA",
      "ticker_display": "NVDA",
      "slug": "NVDA",
      "name": "NVIDIA",
      "mcap_usd": 4864327286784,
      "is_leader": true,
      "gap_pct_from_rank1": 0.0
    },
    {
      "rank": 2,
      "ticker": "AAPL",
      "ticker_display": "AAPL",
      "slug": "AAPL",
      "name": "Apple",
      "mcap_usd": 4386085142528,
      "is_leader": false,
      "gap_pct_from_rank1": 9.8
    },
    {
      "rank": 3,
      "ticker": "GOOGL",
      "ticker_display": "GOOG",
      "slug": "GOOG",
      "name": "Alphabet (Google)",
      "mcap_usd": 4218429636608,
      "is_leader": false,
      "gap_pct_from_rank1": 13.3
    },
    {
      "rank": 4,
      "ticker": "MSFT",
      "ticker_display": "MSFT",
      "slug": "MSFT",
      "name": "Microsoft",
      "mcap_usd": 2779385954304,
      "is_leader": false,
      "gap_pct_from_rank1": 42.9
    },
    {
      "rank": 5,
      "ticker": "AMZN",
      "ticker_display": "AMZN",
      "slug": "AMZN",
      "name": "Amazon",
      "mcap_usd": 2520499617792,
      "is_leader": false,
      "gap_pct_from_rank1": 48.2
    },
    {
      "rank": 6,
      "ticker": "TSM",
      "ticker_display": "TSM",
      "slug": "TSM",
      "name": "TSMC",
      "mcap_usd": 2277017649152,
      "is_leader": false,
      "gap_pct_from_rank1": 53.2
    },
    {
      "rank": 7,
      "ticker": "SPCX",
      "ticker_display": "SPCX",
      "slug": "SPCX",
      "name": "SpaceX",
      "mcap_usd": 2082707210240,
      "is_leader": false,
      "gap_pct_from_rank1": 57.2
    },
    {
      "rank": 8,
      "ticker": "AVGO",
      "ticker_display": "AVGO",
      "slug": "AVGO",
      "name": "Broadcom",
      "mcap_usd": 1809093754880,
      "is_leader": false,
      "gap_pct_from_rank1": 62.8
    },
    {
      "rank": 9,
      "ticker": "2222.SR",
      "ticker_display": "2222.SR",
      "slug": "2222.SR",
      "name": "Saudi Aramco",
      "mcap_usd": 1699969913201,
      "is_leader": false,
      "gap_pct_from_rank1": 65.1
    },
    {
      "rank": 10,
      "ticker": "TSLA",
      "ticker_display": "TSLA",
      "slug": "TSLA",
      "name": "Tesla",
      "mcap_usd": 1445352701952,
      "is_leader": false,
      "gap_pct_from_rank1": 70.3
    },
    {
      "rank": 11,
      "ticker": "META",
      "ticker_display": "META",
      "slug": "META",
      "name": "Meta Platforms (Facebook)",
      "mcap_usd": 1432521146368,
      "is_leader": false,
      "gap_pct_from_rank1": 70.6
    },
    {
      "rank": 12,
      "ticker": "005930.KS",
      "ticker_display": "005930.KS",
      "slug": "005930.KS",
      "name": "Samsung",
      "mcap_usd": 1326163645422,
      "is_leader": false,
      "gap_pct_from_rank1": 72.7
    },
    {
      "rank": 13,
      "ticker": "MU",
      "ticker_display": "MU",
      "slug": "MU",
      "name": "Micron Technology",
      "mcap_usd": 1215437864960,
      "is_leader": false,
      "gap_pct_from_rank1": 75.0
    },
    {
      "rank": 14,
      "ticker": "000660.KS",
      "ticker_display": "000660.KS",
      "slug": "000660.KS",
      "name": "SK Hynix",
      "mcap_usd": 1181565459943,
      "is_leader": false,
      "gap_pct_from_rank1": 75.7
    },
    {
      "rank": 15,
      "ticker": "BRK-B",
      "ticker_display": "BRK-B",
      "slug": "BRK-B",
      "name": "Berkshire Hathaway",
      "mcap_usd": 1064730820608,
      "is_leader": false,
      "gap_pct_from_rank1": 78.1
    },
    {
      "rank": 16,
      "ticker": "LLY",
      "ticker_display": "LLY",
      "slug": "LLY",
      "name": "Eli Lilly",
      "mcap_usd": 982119350272,
      "is_leader": false,
      "gap_pct_from_rank1": 79.8
    },
    {
      "rank": 17,
      "ticker": "WMT",
      "ticker_display": "WMT",
      "slug": "WMT",
      "name": "Walmart",
      "mcap_usd": 956242788352,
      "is_leader": false,
      "gap_pct_from_rank1": 80.3
    },
    {
      "rank": 18,
      "ticker": "JPM",
      "ticker_display": "JPM",
      "slug": "JPM",
      "name": "JPMorgan Chase",
      "mcap_usd": 896376897536,
      "is_leader": false,
      "gap_pct_from_rank1": 81.6
    },
    {
      "rank": 19,
      "ticker": "AMD",
      "ticker_display": "AMD",
      "slug": "AMD",
      "name": "AMD",
      "mcap_usd": 846004551680,
      "is_leader": false,
      "gap_pct_from_rank1": 82.6
    },
    {
      "rank": 20,
      "ticker": "ASML",
      "ticker_display": "ASML",
      "slug": "ASML",
      "name": "ASML",
      "mcap_usd": 684877545472,
      "is_leader": false,
      "gap_pct_from_rank1": 85.9
    },
    {
      "rank": 21,
      "ticker": "INTC",
      "ticker_display": "INTC",
      "slug": "INTC",
      "name": "Intel",
      "mcap_usd": 680723939328,
      "is_leader": false,
      "gap_pct_from_rank1": 86.0
    },
    {
      "rank": 22,
      "ticker": "V",
      "ticker_display": "V",
      "slug": "V",
      "name": "Visa",
      "mcap_usd": 628564295680,
      "is_leader": false,
      "gap_pct_from_rank1": 87.1
    },
    {
      "rank": 23,
      "ticker": "XOM",
      "ticker_display": "XOM",
      "slug": "XOM",
      "name": "Exxon Mobil",
      "mcap_usd": 579691544576,
      "is_leader": false,
      "gap_pct_from_rank1": 88.1
    },
    {
      "rank": 24,
      "ticker": "JNJ",
      "ticker_display": "JNJ",
      "slug": "JNJ",
      "name": "Johnson & Johnson",
      "mcap_usd": 566418145280,
      "is_leader": false,
      "gap_pct_from_rank1": 88.4
    },
    {
      "rank": 25,
      "ticker": "ORCL",
      "ticker_display": "ORCL",
      "slug": "ORCL",
      "name": "Oracle",
      "mcap_usd": 490279567360,
      "is_leader": false,
      "gap_pct_from_rank1": 89.9
    }
  ]
}